instantmailer/__init__.py
instantmailer/mail.py
instantmailer-1.0.3.dist-info/LICENSE
instantmailer-1.0.3.dist-info/METADATA
instantmailer-1.0.3.dist-info/WHEEL
instantmailer-1.0.3.dist-info/top_level.txt
instantmailer-1.0.3.dist-info/RECORD
