Metadata-Version: 2.1
Name: instantmailer
Version: 1.0.3
Summary: UNKNOWN
Home-page: https://github.com/Pythonastics/instant-mailer
Author: mischievousdev
Author-email: miscdev.py@gmail.com
License: MIT
Keywords: gmail email wrapper
Platform: UNKNOWN
